config2/__init__.py
config2/__init__.pyc
config2/config.py
config2/config.pyc
config2/serializers/__init__.py
config2/serializers/json_.py
config2/serializers/yaml_.py
config2/tests/__init__.py
config2/tests/__main__.py
config2/tests/helper.py
config2/tests/test_config.py
config2/tests/__fixtures__/bar/requirements.txt
config2/tests/__fixtures__/bar/setup.py
config2/tests/__fixtures__/bar/config/custom-environment-variables.yml
config2/tests/__fixtures__/bar/config/default.yml
config2/tests/__fixtures__/baz/requirements.txt
config2/tests/__fixtures__/baz/setup.py
config2/tests/__fixtures__/baz/config/default.yml
config2/tests/__fixtures__/config/default+development.yml
config2/tests/__fixtures__/config/default+foo.yml
config2/tests/__fixtures__/config/default+production.yml
config2/tests/__fixtures__/foo/requirements.txt
config2/tests/__fixtures__/foo/setup.py
config2/tests/__fixtures__/foo/config/custom-environment-variables.yml
config2/tests/__fixtures__/foo/config/default.yml
config2/tests/__fixtures__/foo/config/development.yml
config2/tests/__fixtures__/foo/config/foo.yml
config2/tests/__fixtures__/foo/config/production.yml
config2/tests/__fixtures__/foo/src/nested/file.py
config2/tests/serializers/__init__.py
config2/tests/serializers/__main__.py
config2/tests/serializers/test_json.py
config2/tests/serializers/test_yaml.py
config2-0.3.2.data/data/config2/tests/__fixtures__/config2/tests/__fixtures__/bar/requirements.txt
config2-0.3.2.data/data/config2/tests/__fixtures__/config2/tests/__fixtures__/bar/setup.py
config2-0.3.2.data/data/config2/tests/__fixtures__/config2/tests/__fixtures__/bar/config/custom-environment-variables.yml
config2-0.3.2.data/data/config2/tests/__fixtures__/config2/tests/__fixtures__/bar/config/default.yml
config2-0.3.2.data/data/config2/tests/__fixtures__/config2/tests/__fixtures__/baz/requirements.txt
config2-0.3.2.data/data/config2/tests/__fixtures__/config2/tests/__fixtures__/baz/setup.py
config2-0.3.2.dist-info/METADATA
config2-0.3.2.dist-info/WHEEL
config2-0.3.2.dist-info/top_level.txt
config2-0.3.2.dist-info/zip-safe
config2-0.3.2.dist-info/RECORD
